pdpbox/__init__.py
pdpbox/_version.py
pdpbox/get_dataset.py
pdpbox/info_plot_utils.py
pdpbox/info_plots.py
pdpbox/pdp.py
pdpbox/pdp_calc_utils.py
pdpbox/pdp_plot_utils.py
pdpbox/utils.py
pdpbox/datasets/otto/otto_data.csv
pdpbox/datasets/otto/otto_info.json
pdpbox/datasets/otto/otto_model.pkl
pdpbox/datasets/ross/ross_data.csv
pdpbox/datasets/ross/ross_info.json
pdpbox/datasets/ross/ross_model.pkl
pdpbox/datasets/titanic/titanic_data.csv
pdpbox/datasets/titanic/titanic_info.json
pdpbox/datasets/titanic/titanic_model.pkl
PDPbox1-0.2.5.dist-info/LICENSE.txt
PDPbox1-0.2.5.dist-info/METADATA
PDPbox1-0.2.5.dist-info/WHEEL
PDPbox1-0.2.5.dist-info/top_level.txt
PDPbox1-0.2.5.dist-info/RECORD
